layerapi/__init__.py
layerapi/py.typed
layerapi/api/__init__.py
layerapi/api/ids_pb2.py
layerapi/api/ids_pb2.pyi
layerapi/api/ids_pb2_grpc.py
layerapi/api/ids_pb2_grpc.pyi
layerapi/api/entity/__init__.py
layerapi/api/entity/account_pb2.py
layerapi/api/entity/account_pb2.pyi
layerapi/api/entity/account_pb2_grpc.py
layerapi/api/entity/account_pb2_grpc.pyi
layerapi/api/entity/account_view_pb2.py
layerapi/api/entity/account_view_pb2.pyi
layerapi/api/entity/account_view_pb2_grpc.py
layerapi/api/entity/account_view_pb2_grpc.pyi
layerapi/api/entity/activity_wrapper_pb2.py
layerapi/api/entity/activity_wrapper_pb2.pyi
layerapi/api/entity/activity_wrapper_pb2_grpc.py
layerapi/api/entity/activity_wrapper_pb2_grpc.pyi
layerapi/api/entity/analysis_tab_configuration_pb2.py
layerapi/api/entity/analysis_tab_configuration_pb2.pyi
layerapi/api/entity/analysis_tab_configuration_pb2_grpc.py
layerapi/api/entity/analysis_tab_configuration_pb2_grpc.pyi
layerapi/api/entity/billing_info_pb2.py
layerapi/api/entity/billing_info_pb2.pyi
layerapi/api/entity/billing_info_pb2_grpc.py
layerapi/api/entity/billing_info_pb2_grpc.pyi
layerapi/api/entity/compute_fabric_pb2.py
layerapi/api/entity/compute_fabric_pb2.pyi
layerapi/api/entity/compute_fabric_pb2_grpc.py
layerapi/api/entity/compute_fabric_pb2_grpc.pyi
layerapi/api/entity/connection_pb2.py
layerapi/api/entity/connection_pb2.pyi
layerapi/api/entity/connection_pb2_grpc.py
layerapi/api/entity/connection_pb2_grpc.pyi
layerapi/api/entity/cron_expression_pb2.py
layerapi/api/entity/cron_expression_pb2.pyi
layerapi/api/entity/cron_expression_pb2_grpc.py
layerapi/api/entity/cron_expression_pb2_grpc.pyi
layerapi/api/entity/dataset_build_pb2.py
layerapi/api/entity/dataset_build_pb2.pyi
layerapi/api/entity/dataset_build_pb2_grpc.py
layerapi/api/entity/dataset_build_pb2_grpc.pyi
layerapi/api/entity/dataset_list_options_pb2.py
layerapi/api/entity/dataset_list_options_pb2.pyi
layerapi/api/entity/dataset_list_options_pb2_grpc.py
layer_api-0.9.384528.dist-info/METADATA
layer_api-0.9.384528.dist-info/WHEEL
layer_api-0.9.384528.dist-info/top_level.txt
layer_api-0.9.384528.dist-info/RECORD
