Metadata-Version: 2.1
Name: layer-api
Version: 0.9.384528
Summary: UNKNOWN
Home-page: UNKNOWN
Author: UNKNOWN
Author-email: UNKNOWN
License: UNKNOWN
Platform: UNKNOWN
Requires-Dist: grpcio-tools (>=1.43.0)
Requires-Dist: protobuf (<3.20,>=3.17.3)
